CHANGES.txt
LICENSE.txt
MANIFEST.in
README.rst
setup.cfg
setup.py
pyramid_analytics/__init__.py
pyramid_analytics/events.py
pyramid_analytics/helpers.py
pyramid_analytics/tests.py
pyramid_analytics.egg-info/PKG-INFO
pyramid_analytics.egg-info/SOURCES.txt
pyramid_analytics.egg-info/dependency_links.txt
pyramid_analytics.egg-info/not-zip-safe
pyramid_analytics.egg-info/requires.txt
pyramid_analytics.egg-info/top_level.txt
pyramid_analytics/templates/analytics.jinja2