Metadata-Version: 1.1
Name: pyramid-analytics
Version: 0.2.1
Summary: Segment.io wrapper for the Pyramid Web Framework
Home-page: https://github.com/dfee/pyramid_analytics
Author: Devin Fee
Author-email: devin.fee@gmail.com
License: BSD-derived (http://www.repoze.org/LICENSE.txt)
Keywords: segment.io analytics pyramid
Platform: UNKNOWN
Classifier: Intended Audience :: Developers
Classifier: Programming Language :: Python
Classifier: Programming Language :: Python :: 2.7
Classifier: Programming Language :: Python :: 3
Classifier: Programming Language :: Python :: 3.2
Classifier: Framework :: Pyramid
